{
	"ジャンナ": {
		"name": "ジャンナ",
		"beats": [
			{
				"name": "パンテオン",
				"delta2": "4.79"
			},
			{
				"name": "アリスター",
				"delta2": "2.50"
			},
			{
				"name": "ラカン",
				"delta2": "2.26"
			},
			{
				"name": "ラックス",
				"delta2": "2.07"
			},
			{
				"name": "レル",
				"delta2": "1.96"
			},
			{
				"name": "モルガナ",
				"delta2": "1.60"
			},
			{
				"name": "ポッピー",
				"delta2": "1.32"
			},
			{
				"name": "レオナ",
				"delta2": "1.09"
			}
		],
		"loses": [
			{
				"name": "セナ",
				"delta2": "-2.24"
			},
			{
				"name": "ユーミ",
				"delta2": "-1.75"
			},
			{
				"name": "ソナ",
				"delta2": "-1.63"
			},
			{
				"name": "ニーコ",
				"delta2": "-1.50"
			},
			{
				"name": "ナミ",
				"delta2": "-1.37"
			},
			{
				"name": "バード",
				"delta2": "-1.21"
			}
		],
		"origins": [
			{
				"name": "スレッシュ",
				"delta2": "-0.03"
			},
			{
				"name": "ヴェル＝コズ",
				"delta2": "0.11"
			}
		],
		"url": "https://lolalytics.com/ja/lol/janna/build/?patch=15.17"
	}
}